pytket/extensions/stim/__init__.py
pytket/extensions/stim/_metadata.py
pytket/extensions/stim/py.typed
pytket/extensions/stim/backends/__init__.py
pytket/extensions/stim/backends/stim_backend.py
pytket_stim-0.26.0.dist-info/licenses/LICENSE
tests/test_stim.py
pytket_stim-0.26.0.dist-info/METADATA
pytket_stim-0.26.0.dist-info/WHEEL
pytket_stim-0.26.0.dist-info/top_level.txt
pytket_stim-0.26.0.dist-info/RECORD
